{"data":{"user":{"name":null,"bio":"Life is like ridding a bike, To keep balance you must move.","isHireable":true,"avatarUrl":"https://avatars.githubusercontent.com/u/59990559?u=efe2cba6c4c9374e00553fede7d36c30246e5c38&v=4","location":null,"pinnedItems":{"totalCount":6,"edges":[{"node":{"name":"ChamnabYun.github.io","description":null,"forkCount":0,"stargazers":{"totalCount":0},"url":"https://github.com/ChamnabYun/ChamnabYun.github.io","id":"R_kgDOGNTBvQ","diskUsage":19254,"primaryLanguage":{"name":"JavaScript","color":"#f1e05a"}}},{"node":{"name":"nestjs-hexagonal","description":null,"forkCount":0,"stargazers":{"totalCount":0},"url":"https://github.com/ChamnabYun/nestjs-hexagonal","id":"R_kgDOIupslw","diskUsage":938,"primaryLanguage":{"name":"TypeScript","color":"#3178c6"}}},{"node":{"name":"Attachment-Service","description":null,"forkCount":0,"stargazers":{"totalCount":0},"url":"https://github.com/ChamnabYun/Attachment-Service","id":"R_kgDOIupygg","diskUsage":177,"primaryLanguage":{"name":"TypeScript","color":"#3178c6"}}},{"node":{"name":"Chrome-Extension-Cache-Cleaner","description":"Chrome extension for clearing browser cache.","forkCount":0,"stargazers":{"totalCount":0},"url":"https://github.com/ChamnabYun/Chrome-Extension-Cache-Cleaner","id":"R_kgDOJrfThg","diskUsage":61,"primaryLanguage":{"name":"CSS","color":"#563d7c"}}},{"node":{"name":"capacitor-community-sqlite","description":"Community plugin for native & electron SQLite databases","forkCount":0,"stargazers":{"totalCount":0},"url":"https://github.com/ChamnabYun/capacitor-community-sqlite","id":"R_kgDOH9zQqQ","diskUsage":32987,"primaryLanguage":{"name":"Swift","color":"#F05138"}}},{"node":{"name":"Tinode-Instant-Messaging","description":"Instant messaging server; backend in Go; iOS, Android, web, command line clients; chatbots","forkCount":0,"stargazers":{"totalCount":0},"url":"https://github.com/ChamnabYun/Tinode-Instant-Messaging","id":"R_kgDOHxJFvw","diskUsage":20162,"primaryLanguage":{"name":"Go","color":"#00ADD8"}}}]}}}}